mslk/__init__.py
mslk/mslk.so
mslk/version.py
mslk/attention/__init__.py
mslk/attention/cutlass_blackwell_fmha/__init__.py
mslk/attention/cutlass_blackwell_fmha/cutlass_blackwell_fmha_custom_op.py
mslk/attention/cutlass_blackwell_fmha/cutlass_blackwell_fmha_interface.py
mslk/attention/flash_attn/__init__.py
mslk/attention/flash_attn/ampere_helpers.py
mslk/attention/flash_attn/barrier.py
mslk/attention/flash_attn/benchmark.py
mslk/attention/flash_attn/blackwell_helpers.py
mslk/attention/flash_attn/block_info.py
mslk/attention/flash_attn/block_sparse_utils.py
mslk/attention/flash_attn/block_sparsity.py
mslk/attention/flash_attn/compute_block_sparsity.py
mslk/attention/flash_attn/copy_utils.py
mslk/attention/flash_attn/cute_dsl_utils.py
mslk/attention/flash_attn/fast_math.py
mslk/attention/flash_attn/flash_bwd.py
mslk/attention/flash_attn/flash_bwd_postprocess.py
mslk/attention/flash_attn/flash_bwd_preprocess.py
mslk/attention/flash_attn/flash_bwd_sm100.py
mslk/attention/flash_attn/flash_bwd_sm90.py
mslk/attention/flash_attn/flash_fwd.py
mslk/attention/flash_attn/flash_fwd_combine.py
mslk/attention/flash_attn/flash_fwd_sm100.py
mslk/attention/flash_attn/hopper_helpers.py
mslk/attention/flash_attn/interface.py
mslk/attention/flash_attn/mask.py
mslk/attention/flash_attn/mma_sm100_desc.py
mslk/attention/flash_attn/named_barrier.py
mslk/attention/flash_attn/pack_gqa.py
mslk/attention/flash_attn/paged_kv.py
mslk/attention/flash_attn/pipeline.py
mslk/attention/flash_attn/seqlen_info.py
mslk/attention/flash_attn/softmax.py
mslk/attention/flash_attn/testing.py
mslk/attention/flash_attn/tile_scheduler.py
mslk/attention/flash_attn/utils.py
mslk/attention/fmha/__init__.py
mslk/attention/fmha/attn_bias.py
mslk/attention/fmha/attn_bias_utils.py
mslk/attention/fmha/ck.py
mslk/attention/fmha/ck_decoder.py
mslk/attention/fmha/ck_splitk.py
mslk/attention/fmha/common.py
mslk/attention/fmha/cutlass.py
mslk/attention/fmha/cutlass_blackwell.py
mslk/attention/fmha/dispatch.py
mslk_cuda_nightly-2026.1.31.dist-info/licenses/LICENSE
mslk_cuda_nightly-2026.1.31.dist-info/METADATA
mslk_cuda_nightly-2026.1.31.dist-info/WHEEL
mslk_cuda_nightly-2026.1.31.dist-info/top_level.txt
mslk_cuda_nightly-2026.1.31.dist-info/RECORD
